notifications_plus/__init__.py
notifications_plus/filters.py
notifications_plus/models.py
notifications_plus/serializers.py
notifications_plus/viewsets.py
django_notifications_plus-0.0.0.dist-info/LICENSE
django_notifications_plus-0.0.0.dist-info/WHEEL
django_notifications_plus-0.0.0.dist-info/METADATA
django_notifications_plus-0.0.0.dist-info/RECORD
